flata/__init__.py
flata/database.py
flata/middlewares.py
flata/operations.py
flata/queries.py
flata/storages.py
flata/utils.py
flata-5.0.0.dist-info/DESCRIPTION.rst
flata-5.0.0.dist-info/METADATA
flata-5.0.0.dist-info/RECORD
flata-5.0.0.dist-info/WHEEL
flata-5.0.0.dist-info/metadata.json
flata-5.0.0.dist-info/top_level.txt
flata-5.0.0.dist-info/zip-safe
tests/__init__.py
tests/conftest.py
tests/test_crud.py
tests/test_flata.py
tests/test_middlewares.py
tests/test_operations.py
tests/test_queries.py
tests/test_storages.py
tests/test_tables.py
tests/test_utils.py
