Metadata-Version: 2.0
Name: flata
Version: 5.0.0
Summary: Flata is inspired by TinyDB and lowdb. It is a tiny, document oriented database optimized for FlatApi and fun :)
Home-page: https://github.com/harryho/flata
Author: Harry Ho
Author-email: harry.ho_long@yahoo.com
License: MIT
